odoo/addons/github_connector/README.rst
odoo/addons/github_connector/__init__.py
odoo/addons/github_connector/__manifest__.py
odoo/addons/github_connector/data/ir_config_parameter.xml
odoo/addons/github_connector/data/ir_cron.xml
odoo/addons/github_connector/demo/github_analysis_rule_demo.xml
odoo/addons/github_connector/demo/github_analysis_rule_group_demo.xml
odoo/addons/github_connector/demo/github_organization.xml
odoo/addons/github_connector/demo/github_organization_serie.xml
odoo/addons/github_connector/i18n/github_connector.pot
odoo/addons/github_connector/migrations/14.0.1.0.0/pre-migration.py
odoo/addons/github_connector/migrations/14.0.2.2.0/post-migration.py
odoo/addons/github_connector/models/__init__.py
odoo/addons/github_connector/models/abstract_github_model.py
odoo/addons/github_connector/models/github_analysis_rule.py
odoo/addons/github_connector/models/github_analysis_rule_group.py
odoo/addons/github_connector/models/github_analysis_rule_info.py
odoo/addons/github_connector/models/github_organization.py
odoo/addons/github_connector/models/github_organization_serie.py
odoo/addons/github_connector/models/github_repository.py
odoo/addons/github_connector/models/github_repository_branch.py
odoo/addons/github_connector/models/github_team.py
odoo/addons/github_connector/models/github_team_partner.py
odoo/addons/github_connector/models/github_team_repository.py
odoo/addons/github_connector/models/res_partner.py
odoo/addons/github_connector/readme/CONFIGURE.rst
odoo/addons/github_connector/readme/CONTRIBUTORS.rst
odoo/addons/github_connector/readme/DESCRIPTION.rst
odoo/addons/github_connector/readme/INSTALL.rst
odoo/addons/github_connector/readme/ROADMAP.rst
odoo/addons/github_connector/readme/USAGE.rst
odoo/addons/github_connector/report/__init__.py
odoo/addons/github_connector/report/github_repository_branch_rule_info_report.py
odoo/addons/github_connector/report/github_repository_branch_rule_info_report_view.xml
odoo14_addon_github_connector-14.0.2.3.0.dist-info/METADATA
odoo14_addon_github_connector-14.0.2.3.0.dist-info/WHEEL
odoo14_addon_github_connector-14.0.2.3.0.dist-info/top_level.txt
odoo14_addon_github_connector-14.0.2.3.0.dist-info/RECORD
