Metadata-Version: 2.1
Name: odoo14-addon-github-connector
Version: 14.0.2.3.0
Summary: Synchronize information from Github repositories
Home-page: https://github.com/OCA/interface-github
Author: Odoo Community Association (OCA), GRAP, Akretion, Tecnativa
Author-email: support@odoo-community.org
License: AGPL-3
Platform: UNKNOWN
Classifier: Programming Language :: Python
Classifier: Framework :: Odoo
Classifier: Framework :: Odoo :: 14.0
Classifier: License :: OSI Approved :: GNU Affero General Public License v3
Requires-Python: >=3.6
Requires-Dist: GitPython
Requires-Dist: PyGithub
Requires-Dist: odoo <14.1dev,>=14.0a
Requires-Dist: pathspec
Requires-Dist: pygount
